dotfilesmgr.py
dotfilesmgr-0.1.4.dist-info/METADATA
dotfilesmgr-0.1.4.dist-info/WHEEL
dotfilesmgr-0.1.4.dist-info/entry_points.txt
dotfilesmgr-0.1.4.dist-info/licenses/LICENSE
dotfilesmgr-0.1.4.dist-info/RECORD
