Metadata-Version: 2.4
Name: dotfilesmgr
Version: 0.1.4
Summary: Simple tool to manage your dotfiles
Project-URL: Repository, https://github.com/J0schu/dotfilemgr
Project-URL: Issues, https://github.com/J0schu/dotfilemgr/issues
Project-URL: Changelog, https://github.com/J0schu/dotfilemgr/releases
Author: J0schu
License-Expression: MIT
License-File: LICENSE
Requires-Python: >=3.8
Requires-Dist: colorama
Requires-Dist: toml
